fake_git/__init__.py
fake_git/fake_git.py
fake_git/fake_git_main.py
fake_git-0.0.13.dist-info/METADATA
fake_git-0.0.13.dist-info/WHEEL
fake_git-0.0.13.dist-info/entry_points.txt
fake_git-0.0.13.dist-info/top_level.txt
fake_git-0.0.13.dist-info/RECORD
