Metadata-Version: 2.1
Name: fake-git
Version: 0.0.13
Summary: Allows to fake git repository
Home-page: https://github.com/brosiak/fake_git
Author: Bartosz Rosiak
Author-email: rosiakbartosz0@gmail.com
License: UNKNOWN
Platform: UNKNOWN
Classifier: Programming Language :: Python
Classifier: Programming Language :: Python :: 3
Classifier: Programming Language :: Python :: 3.6
Requires-Dist: docopt
